[
  {
    "id": 1765909652040,
    "name": "tes tes",
    "image": null,
    "top": "26%",
    "left": "57%",
    "duration": 20,
    "delay": -17.48530452645106,
    "size": "calc(clamp(50px, 12vw, 90px) * 0.86)",
    "title": "Sendirian Tapi Lulus",
    "rarity": "Legendary"
  },
  {
    "id": 1765909746380,
    "name": "aadasd",
    "image": null,
    "top": "7%",
    "left": "71%",
    "duration": 21,
    "delay": -14.080794839273011,
    "size": "calc(clamp(50px, 12vw, 90px) * 0.90)",
    "title": "Anak Baik",
    "rarity": "Common"
  }
]